<tv generator-info-url="https://github.com/amazeyourself/m3u"><channel id="whiplash"><display-name>Whiplash</display-name><icon src="https://whiplash.cc/assets/img/channels/whiplash.png" /></channel><programme channel="whiplash" start="20260526051500 -0400" stop="20260526060000 -0400"><title>OFF-AIR</title><desc /><sub-title /></programme><channel id="whiplashii"><display-name>Whiplash II</display-name><icon src="https://whiplash.cc/assets/img/channels/whiplash2.png" /></channel><programme channel="whiplashii" start="20260526054702 -0400" stop="20260526061131 -0400"><title>The Office (US)</title><desc>Dwight must confront his fear of public speaking when he is named Dunder-Mifflin's Salesman of the Year. To prepare for a big convention where he is set to give a speech, Dwight turns to Michael to guide him in his quest to conquer the fear. Meanwhile, Pam gets wrapped up with wedding plans, but Jim has plans of a different sort: an escape route out of Dunder-Mifflin and Scranton, at least for long enough so that he doesn't have to witness Pam's wedding. While all of this is happening, the staffers battle it out over control of the thermostat.</desc><sub-title>Dwight's Speech</sub-title></programme><channel id="whiplashcinema"><display-name>Whiplash Cinema</display-name><icon src="https://whiplash.cc/assets/img/channels/whiplashcinema.png" /></channel><programme channel="whiplashcinema" start="20260526040418 -0400" stop="20260526060639 -0400"><title>Pom Poko</title><desc>As the human city development encroaches on the raccoon dog population's forest and meadow habitat, the raccoon dogs find themselves faced with the very real possibility of extinction. In response, the raccoon dogs engage in a desperate struggle to stop the construction and preserve their home.</desc><sub-title /></programme><channel id="atlas"><display-name>Atlas</display-name><icon src="https://whiplash.cc/assets/img/channels/atlas.png" /></channel><programme channel="atlas" start="20260526053933 -0400" stop="20260526060729 -0400"><title>Four in a Bed</title><desc>An afternoon of fairground fun turns a bit fighty in Cleethorpes. And some harsh feedback leaves the host Gill feeling a bit sad.</desc><sub-title>Amber Guest House</sub-title></programme></tv>